{
    "metadata": {
        "title": "truffle",
        "aliases": [],
        "tags": [
            "enemies",
            "bosses"
        ],
        "keys": {}
    },
    "embed": {
        "color": 12846604,
        "url": "https://wildfrostwiki.com/Truffle",
        "description": "**Truffle** is a Boss type enemy that the player can encounter.",
        "fields": [
            {
                "inline": false,
                "name": "Stats",
                "value": "<&Health&> 110 | <&Attack&> 4 | <&Counter&> 4"
            },
            {
                "inline": false,
                "name": "Effects",
                "value": "Split when 10 <&Health&> lost"
            }
        ],
        "footer": {
            "text": "<&Footer&>"
        },
        "image": {
            "url": "https://wildfrostwiki.com/images/e/e2/Truffle_%28SummonBoss%29.png"
        },
        "title": "Truffle"
    }
}